[
    {
        "image": "https://imagedelivery.net/a5r9Tc1KZUombyb_AZ4nqA/d74e4c32-cce3-45d8-5810-77e32dbc5600/hd",
        "zipUrl": "https://www.mediafire.com/file/knet0jwtsjh132a/SERPpokedrockR4.zip/file?hash=ZSN6kRh6Ytdoiy9jnOwGGWjjbybBjQg8eIogrnN2f1nG0t45cTetBUQU6ktu06NJ",
        "title": "Serp Pokedrock Gen 4 HD Addon For Minecraft",
        "description": "SERP Pokedrock 1 Addon ·Pokedrock Anime Sounds ·P",
        "stars": "5",
        "ratingNum": "5",
        "itemNumDownload": "1",
        "itemNumViews": "1",
        "itemSize": "2.1 Mb"
    },
    {
        "image": "https://imagedelivery.net/a5r9Tc1KZUombyb_AZ4nqA/19714dfd-a8b4-4564-0fa9-0971c6378900/hd",
        "zipUrl": "https://www.mediafire.com/download/ujh1t66s71uzwng",
        "title": "the Ultimate mon Mod",
        "description": "This mod features a variety of Pkmon, including mega evolutions and dynamax forms",
        "stars": "5",
        "ratingNum": "5",
        "itemNumDownload": "1",
        "itemNumViews": "1",
        "itemSize": "2.09 Mb"
    },
     {
        "image": "https://imagedelivery.net/a5r9Tc1KZUombyb_AZ4nqA/d96758d8-2c1e-41ee-b6c9-72402cf7d300/hd",
        "zipUrl": "https://mega.nz/file/Cj4XWRbY#MbBkXNMWS7tAQ2-o28PL42j6sfBKBLF50lDAZpOFVBI",
        "title": "MOD COBBLEMON",
        "description": "MOD COBBLEMON",
        "stars": "5",
        "ratingNum": "5",
        "itemNumDownload": "1",
        "itemNumViews": "1",
        "itemSize": "1.46 Mb"
    },
     {
        "image": "https://imagedelivery.net/a5r9Tc1KZUombyb_AZ4nqA/a1d4d2d4-e80c-4958-1d8d-14319de9fd00/hd",
        "zipUrl": "https://www.mediafire.com/file/yh4bffclpbpt9c1/Skibidi+Toilet+Mod.mcaddon/file",
        "title": "Skibidi Toilet RP V.9.4 ·Ghost Block Addon ·Ghost Block BEH",
        "description": "This is the Resources file of Ghost Block Addon, also download the behavior pack to completely use it. To know how it work read in in MCPEDL or watch the video below.",
        "stars": "5",
        "ratingNum": "5",
        "itemNumDownload": "1",
        "itemNumViews": "1",
        "itemSize": "1.1 Mb"
    },
     {
        "image": "https://imagedelivery.net/a5r9Tc1KZUombyb_AZ4nqA/cd4d2746-f681-482b-97a2-deb2e0743100/hd",
        "zipUrl": "https://www.mediafire.com/file/dxu5cvvwudxtykz/Cobblemon_Updated_1.4.1.zip/file",
        "title": "Cobblemon Updated - 1.20.1",
        "description": "bblemon Updated is a small pack which features the new best P mod, Cobblemon",
        "stars": "5",
        "ratingNum": "5",
        "itemNumDownload": "1",
        "itemNumViews": "1",
        "itemSize": "2.3 Mb"
    },
    {
        "image": "https://imagedelivery.net/a5r9Tc1KZUombyb_AZ4nqA/443787fd-e37a-47b7-2541-474b99ac2900/hd",
        "zipUrl": "https://www.mediafire.com/file/i383lv6bcj9avps/Cobblemon-Mod-Forge-1.19.2.jar/file",
        "title": "Cobblemon Mod (1.19.2) – Immersive",
        "description": "Cobblemon Mod (1.19.2) – Immersive",
        "stars": "5",
        "ratingNum": "5",
        "itemNumDownload": "1",
        "itemNumViews": "1",
        "itemSize": "56.32 Mb"
    }
]
